listish.py
listish-1.0.dist-info/DESCRIPTION.rst
listish-1.0.dist-info/METADATA
listish-1.0.dist-info/RECORD
listish-1.0.dist-info/WHEEL
listish-1.0.dist-info/metadata.json
listish-1.0.dist-info/top_level.txt
