Metadata-Version: 2.0
Name: listish
Version: 1.0
Summary: 
